setup.py
pyageng/__init__.py
pyageng.egg-info/PKG-INFO
pyageng.egg-info/SOURCES.txt
pyageng.egg-info/dependency_links.txt
pyageng.egg-info/top_level.txt