Metadata-Version: 1.1
Name: pyageng
Version: 0.0.1
Summary: Code for the book "Measurements and Data Analysis for Agricultural Engineers using Python"
Home-page: http://pyageng.mpastell.com
Author: Matti Pastell
Author-email: matti.pastell@helsinki.fi
License: LICENSE.txt
Platform: UNKNOWN
Classifier: Development Status :: 5 - Production/Stable
Classifier: Intended Audience :: Science/Research
Classifier: Topic :: Scientific/Engineering
Classifier: License :: OSI Approved :: MIT License
Classifier: Programming Language :: Python :: 2.7
Classifier: Programming Language :: Python :: 3.4
